{
  "d": [
    {
      "i": {
        "height": 999,
        "imageUrl": "https://m.media-amazon.com/images/M/MV5BMTNkMDM2NjctM2MwYi00MTc5LWFjMzUtNzI2MTIxN2YyYWQzXkEyXkFqcGdeQXVyMTY3ODkyNDkz._V1_.jpg",
        "width": 666
      },
      "id": "tt17423376",
      "l": "Captain Avispa",
      "q": "feature",
      "qid": "movie",
      "rank": 56570,
      "s": "Luis Fonsi, Joy Huerta",
      "y": 2024
    },
    {
      "i": {
        "height": 2400,
        "imageUrl": "https://m.media-amazon.com/images/M/MV5BM2IxNjg4MmQtNmJmMi00MjNlLWFlMjAtMzI4M2FkNTFjMTU1XkEyXkFqcGdeQXVyMjUzMTYzMDI@._V1_.jpg",
        "width": 1625
      },
      "id": "tt14225838",
      "l": "Io Capitano",
      "q": "feature",
      "qid": "movie",
      "rank": 3619,
      "s": "Seydou Sarr, Moustapha Fall",
      "y": 2023
    },
    {
      "i": {
        "height": 2500,
        "imageUrl": "https://m.media-amazon.com/images/M/MV5BZTk2NTUxZDItN2Y1Ni00MDFjLTg4OWItMWY3M2Q2OGNiODUwXkEyXkFqcGc@._V1_.jpg",
        "width": 1688
      },
      "id": "tt14513804",
      "l": "Captain America: Brave New World",
      "q": "feature",
      "qid": "movie",
      "rank": 680,
      "s": "Harrison Ford, Liv Tyler",
      "y": 2025
    },
    {
      "i": {
        "height": 1023,
        "imageUrl": "https://m.media-amazon.com/images/M/MV5BZmRjN2QwNWUtOGZlNC00ZGY2LTg2NzgtNWFiMTEwNzEyMGEwXkEyXkFqcGc@._V1_.jpg",
        "width": 756
      },
      "id": "tt0053696",
      "l": "Captain Blood",
      "q": "feature",
      "qid": "movie",
      "rank": 126805,
      "s": "Jean Marais, Bourvil",
      "y": 1960
    },
    {
      "i": {
        "height": 4096,
        "imageUrl": "https://m.media-amazon.com/images/M/MV5BMmJlNTAyNzEtMzIxOS00Zjg4LWEyYTgtYWUyYTQ1YmE5ZjM1XkEyXkFqcGdeQXVyNDYwNTY0NTY@._V1_.jpg",
        "width": 3277
      },
      "id": "nm9873540",
      "l": "Sebastián Capitán Viveros",
      "rank": 166996,
      "s": "Actor, Spider-Man: Far from Home (2019)"
    },
    {
      "i": {
        "height": 597,
        "imageUrl": "https://m.media-amazon.com/images/M/MV5BMGE2MDEzMjEtMzE2YS00MjMyLWFiNjUtZGJjNTUyNzk3ZTczXkEyXkFqcGc@._V1_.jpg",
        "width": 426
      },
      "id": "tt10483610",
      "l": "Capitani",
      "q": "TV series",
      "qid": "tvSeries",
      "rank": 21585,
      "s": "Luc Schiltz, Sophie Mousel",
      "y": 2019,
      "yr": "2019-2022"
    },
    {
      "i": {
        "height": 2048,
        "imageUrl": "https://m.media-amazon.com/images/M/MV5BMjE5OTM0OTY5NF5BMl5BanBnXkFtZTgwMDcxOTQ3ODE@._V1_.jpg",
        "width": 1382
      },
      "id": "tt3553976",
      "l": "Captain Fantastic",
      "q": "feature",
      "qid": "movie",
      "rank": 1981,
      "s": "Viggo Mortensen, George MacKay",
      "y": 2016
    },
    {
      "i": {
        "height": 983,
        "imageUrl": "https://m.media-amazon.com/images/M/MV5BYzNmYzlhMmYtYjYzNi00NTIxLTg4YTMtNWM1OGZhMzUyZDk1XkEyXkFqcGdeQXVyMjU5OTg5NDc@._V1_.jpg",
        "width": 699
      },
      "id": "tt0103203",
      "l": "The Voyage of Captain Fracassa",
      "q": "feature",
      "qid": "movie",
      "rank": 80650,
      "s": "Vincent Perez, Emmanuelle Béart",
      "y": 1990
    }
  ],
  "q": "capitan",
  "v": 1
}
